PasswordGeneratorTools/PasswordGeneratorTools.py
PasswordGeneratorTools/__init__.py
password_generator_tools-0.2.dist-info/LICENSE
password_generator_tools-0.2.dist-info/METADATA
password_generator_tools-0.2.dist-info/WHEEL
password_generator_tools-0.2.dist-info/top_level.txt
password_generator_tools-0.2.dist-info/RECORD
